scons_tool_archives-0.2.1-py3.8-nspkg.pth
sconstool/archives/__init__.py
sconstool/archives/about.py
scons_tool_archives-0.2.1.dist-info/METADATA
scons_tool_archives-0.2.1.dist-info/WHEEL
scons_tool_archives-0.2.1.dist-info/namespace_packages.txt
scons_tool_archives-0.2.1.dist-info/top_level.txt
scons_tool_archives-0.2.1.dist-info/RECORD
