Metadata-Version: 2.1
Name: scons-tool-archives
Version: 0.2.1
Summary: SCons tool to create archives
Home-page: https://github.com/ptomulik/scons-tool-archives
Author: Paweł Tomulik
Author-email: ptomulik@meil.pw.edu.pl
License: UNKNOWN
Platform: UNKNOWN
Requires-Python: >=2.7
